llama_index/readers/airbyte_typeform/__init__.py
llama_index/readers/airbyte_typeform/base.py
llama_index_readers_airbyte_typeform-0.4.1.dist-info/METADATA
llama_index_readers_airbyte_typeform-0.4.1.dist-info/WHEEL
llama_index_readers_airbyte_typeform-0.4.1.dist-info/licenses/LICENSE
llama_index_readers_airbyte_typeform-0.4.1.dist-info/RECORD
