Metadata-Version: 2.4
Name: llama-index-readers-airbyte-typeform
Version: 0.4.1
Summary: llama-index readers airbyte_typeform integration
Author-email: Your Name <you@example.com>
Maintainer: flash1293
License-Expression: MIT
License-File: LICENSE
Requires-Python: <4.0,>=3.9
Requires-Dist: llama-index-core<0.15,>=0.13.0
Requires-Dist: llama-index-readers-airbyte-cdk<0.5,>=0.4.0
